Andreani_QA_parameters/Parameters.py
Andreani_QA_parameters/__init__.py
Andreani_QA_Parameters-0.0.23.dist-info/METADATA
Andreani_QA_Parameters-0.0.23.dist-info/WHEEL
Andreani_QA_Parameters-0.0.23.dist-info/top_level.txt
Andreani_QA_Parameters-0.0.23.dist-info/RECORD
