Metadata-Version: 2.1
Name: Andreani_QA_Parameters
Version: 0.0.23
Summary: Parametros + Encriptor para ejecución de casos automatizados
Home-page: UNKNOWN
Author: AndreaniTesting
Author-email: user_appglatest@andreani.com
License: MIT
Platform: UNKNOWN
